vn_fullname_generator/__init__.py
vn_fullname_generator/generate.py
vn_fullname_generator/generator.py
vn_fullname_generator/main.py
vn_fullname_generator/data/__init__.py
vn_fullname_generator/data/female.name
vn_fullname_generator/data/first.name
vn_fullname_generator/data/male.name
vn_fullname_generator-0.0.2.dist-info/LICENSE
vn_fullname_generator-0.0.2.dist-info/METADATA
vn_fullname_generator-0.0.2.dist-info/WHEEL
vn_fullname_generator-0.0.2.dist-info/top_level.txt
vn_fullname_generator-0.0.2.dist-info/RECORD
