Metadata-Version: 2.1
Name: vn_fullname_generator
Version: 0.0.2
Summary: Generate Vietnamese Fullname
Home-page: https://github.com/lhlong/vietnamese-fullname-generator
Author: Lh Long
Author-email: lhlong@github.com
License: UNKNOWN
Project-URL: Bug Tracker, https://github.com/lhlong/vietnamese-fullname-generator/issues
Platform: UNKNOWN
Classifier: Programming Language :: Python :: 3
Classifier: License :: OSI Approved :: MIT License
Classifier: Operating System :: OS Independent
Requires-Python: >=3.7
